servicecatalog_product_maker/__init__.py
servicecatalog_product_maker/product_maker.py
servicecatalog_product_maker-0.1.0.dist-info/METADATA
servicecatalog_product_maker-0.1.0.dist-info/WHEEL
servicecatalog_product_maker-0.1.0.dist-info/entry_points.txt
servicecatalog_product_maker-0.1.0.dist-info/top_level.txt
servicecatalog_product_maker-0.1.0.dist-info/RECORD
