Metadata-Version: 2.1
Name: servicecatalog-product-maker
Version: 0.1.0
Summary: Helpers to make creating AWS Service Catalog products easier
Home-page: https://github.com/eamonnfaherty/service-catalog-product-maker
Author: Eamonn Faherty
Author-email: python-packages@designandsolve.co.uk
License: UNKNOWN
Platform: UNKNOWN
Classifier: Programming Language :: Python :: 3
Classifier: License :: OSI Approved :: MIT License
Classifier: Operating System :: OS Independent
Requires-Dist: click
Requires-Dist: requests
Requires-Dist: pyyaml
Requires-Dist: cfn-flip
